odutil/__init__.py
odutil/analysis.py
odutil/process.py
odutil/visual.py
odutil-0.0.22.dist-info/LICENSE
odutil-0.0.22.dist-info/METADATA
odutil-0.0.22.dist-info/WHEEL
odutil-0.0.22.dist-info/top_level.txt
odutil-0.0.22.dist-info/RECORD
