Metadata-Version: 2.1
Name: odutil
Version: 0.0.22
Summary: A group of utils for object detection.
Home-page: https://github.com/ZillyRex/odutil
Author: ZillyRex
Author-email: zillyrain@gmail.com
License: UNKNOWN
Platform: UNKNOWN
Classifier: Programming Language :: Python :: 3
Classifier: License :: OSI Approved :: GNU General Public License v3 (GPLv3)
Classifier: Operating System :: OS Independent
